pyoploverz/__init__.py
pyoploverz/api.py
pyoploverz/base.py
pyoploverz/style.py
pyoploverz/util.py
pyoploverz-0.0.4.dist-info/LICENSE
pyoploverz-0.0.4.dist-info/METADATA
pyoploverz-0.0.4.dist-info/WHEEL
pyoploverz-0.0.4.dist-info/top_level.txt
pyoploverz-0.0.4.dist-info/RECORD
