Metadata-Version: 2.1
Name: pyoploverz
Version: 0.0.4
Summary: Unofficial wrapper anime from oploverz.in
Home-page: https://github.com/dyseo/PyOpLoverz
Author: Dyseo
Author-email: katro.coplax@gmail.com
License: UNKNOWN
Platform: UNKNOWN
Classifier: Programming Language :: Python :: 3.6
Classifier: Programming Language :: Python :: 3.7
Classifier: License :: OSI Approved :: MIT License
Classifier: Operating System :: OS Independent
Classifier: Topic :: Software Development :: Libraries :: Python Modules
Classifier: Topic :: Utilities
Classifier: Topic :: Internet
